{
  "IsEncrypted": false,
  "Values": {
    "AzureWebJobsStorage": "UseDevelopmentStorage=true",
    "FUNCTIONS_WORKER_RUNTIME": "node",
    "COSMOS_ENDPOINT": "https://<account>.documents.azure.com:443/",
    "COSMOS_DATABASE_NAME": "autoinsight",
    "COSMOS_CONNECTIONS_CONTAINER": "fabricConnections",
    "COSMOS_MAPPINGS_CONTAINER": "semanticMappings",
    "COSMOS_ANALYSIS_RUNS_CONTAINER": "analysisRuns",
    "COSMOS_ANALYSIS_RESULTS_CONTAINER": "analysisResults",
    "COSMOS_SEGMENTS_CONTAINER": "segments",
    "COSMOS_AUDIT_CONTAINER": "auditLogs",
    "ANALYSIS_WORKER_URL": "https://<python-function-app>.azurewebsites.net/api/analysis/run",
    "ANALYSIS_WORKER_KEY": "<function-key>"
  }
}
